com/__init__.py
com/dakshata/__init__.py
com/dakshata/autotrader/__init__.py
com/dakshata/autotrader/api/AutoTrader.py
com/dakshata/autotrader/api/__init__.py
com/dakshata/data/__init__.py
com/dakshata/data/model/__init__.py
com/dakshata/data/model/common/OperationResponse.py
com/dakshata/data/model/common/__init__.py
com/dakshata/trading/__init__.py
com/dakshata/trading/model/__init__.py
com/dakshata/trading/model/platform/PlatformHolding.py
com/dakshata/trading/model/platform/PlatformMargin.py
com/dakshata/trading/model/platform/PlatformOrder.py
com/dakshata/trading/model/platform/PlatformPosition.py
com/dakshata/trading/model/platform/__init__.py
com/dakshata/trading/model/portfolio/CoreOrder.py
com/dakshata/trading/model/portfolio/Position.py
com/dakshata/trading/model/portfolio/__init__.py
tests/__init__.py
tests/test_AutoTrader.py
AutoTrader_Web_API_Stocks_Developer-1.3.5.dist-info/LICENSE
AutoTrader_Web_API_Stocks_Developer-1.3.5.dist-info/METADATA
AutoTrader_Web_API_Stocks_Developer-1.3.5.dist-info/WHEEL
AutoTrader_Web_API_Stocks_Developer-1.3.5.dist-info/top_level.txt
AutoTrader_Web_API_Stocks_Developer-1.3.5.dist-info/RECORD
