Metadata-Version: 2.1
Name: AutoTrader-Web-API-Stocks-Developer
Version: 1.3.5
Summary: Python trading API library for Zerodha, Upstox, AliceBlue, Finvasia, Angel One, Fyers, IIFL, 5Paisa, Profitmart, Mastertrust, Edelweiss, Motilal Oswal, Kotak Securities
Home-page: https://github.com/Pritesh-Mhatre/python-library
Author: Pritesh Mhatre
Author-email: help@stocksdeveloper.in
Classifier: Programming Language :: Python :: 3
Classifier: Development Status :: 5 - Production/Stable
Classifier: License :: OSI Approved :: GNU General Public License v3 (GPLv3)
Classifier: Operating System :: OS Independent
Classifier: Intended Audience :: Information Technology
Classifier: Topic :: Office/Business :: Financial :: Investment
Requires-Python: >=3.6
License-File: LICENSE
Requires-Dist: requests
